{"ose":"S","raceid":"KYD00","pages":[{"firstCounty":"Adair","lastCounty":"Woodford"}],"candidates":[{"lname":"Clinton","party":"D","pctDecimal":"46.8","winner":true},{"lname":"Sanders","party":"D","pctDecimal":"46.3","winner":false}],"race":{"status":"called","raceid":"KYD00","state":"Kentucky","electiondate":"20160517","ncon":false,"keyrace":false,"etype":"D","rtype":"P","race":"Democratic Primary-President","title2":"","pollclose":1463526000000,"xpoll":false,"cresults":true,"cmap":true},"counties":[{"co_id":21001,"name":"Adair","countycode":21001,"race":{"ts":1463595277000,"pctsrep":100,"sw":true,"candidates":[{"id":1746,"fname":"Hillary","mname":"","lname":"Clinton","suffix":"","usesuffix":false,"party":"D","inrace":true,"nominee":true,"winner":true,"vpct":50,"pctDecimal":"49.6","inc":false,"votes":466,"cvotes":"466"},{"id":1445,"fname":"Bernie","mname":"","lname":"Sanders","suffix":"","usesuffix":false,"party":"D","inrace":true,"nominee":false,"winner":false,"vpct":44,"pctDecimal":"43.7","inc":false,"votes":410,"cvotes":"410"}],"rd":"55","rd_k":"55","pd_k":"5"}},{"co_id":21003,"name":"Allen","countycode":21003,"race":{"ts":1463595277000,"pctsrep":100,"sw":true,"candidates":[{"id":1445,"fname":"Bernie","mname":"","lname":"Sanders","suffix":"","usesuffix":false,"party":"D","inrace":true,"nominee":false,"winner":false,"vpct":47,"pctDecimal":"47.4","inc":false,"votes":440,"cvotes":"440"},{"id":1746,"fname":"Hillary","mname":"","lname":"Clinton","suffix":"","usesuffix":false,"party":"D","inrace":true,"nominee":true,"winner":true,"vpct":46,"pctDecimal":"46.0","inc":false,"votes":427,"cvotes":"427"}],"rd":"55","rd_k":"55","pd_k":"5"}},{"co_id":21005,"name":"Anderson","countycode":21005,"race":{"ts":1463595277000,"pctsrep":100,"sw":true,"candidates":[{"id":1445,"fname":"Bernie","mname":"","lname":"Sanders","suffix":"","usesuffix":false,"party":"D","inrace":true,"nominee":false,"winner":false,"vpct":52,"pctDecimal":"52.4","inc":false,"votes":1649,"cvotes":"1,649"},{"id":1746,"fname":"Hillary","mname":"","lname":"Clinton","suffix":"","usesuffix":false,"party":"D","inrace":true,"nominee":true,"winner":true,"vpct":36,"pctDecimal":"36.0","inc":false,"votes":1132,"cvotes":"1,132"}],"rd":"55","rd_k":"55","pd_k":"5"}},{"co_id":21007,"name":"Ballard","countycode":21007,"race":{"ts":1463595277000,"pctsrep":100,"sw":true,"candidates":[{"id":1445,"fname":"Bernie","mname":"","lname":"Sanders","suffix":"","usesuffix":false,"party":"D","inrace":true,"nominee":false,"winner":false,"vpct":52,"pctDecimal":"52.0","inc":false,"votes":659,"cvotes":"659"},{"id":1746,"fname":"Hillary","mname":"","lname":"Clinton","suffix":"","usesuffix":false,"party":"D","inrace":true,"nominee":true,"winner":true,"vpct":32,"pctDecimal":"32.0","inc":false,"votes":405,"cvotes":"405"}],"rd":"55","rd_k":"55","pd_k":"5"}},{"co_id":21009,"name":"Barren","countycode":21009,"race":{"ts":1463595277000,"pctsrep":100,"sw":true,"candidates":[{"id":1445,"fname":"Bernie","mname":"","lname":"Sanders","suffix":"","usesuffix":false,"party":"D","inrace":true,"nominee":false,"winner":false,"vpct":50,"pctDecimal":"49.9","inc":false,"votes":2653,"cvotes":"2,653"},{"id":1746,"fname":"Hillary","mname":"","lname":"Clinton","suffix":"","usesuffix":false,"party":"D","inrace":true,"nominee":true,"winner":true,"vpct":37,"pctDecimal":"37.2","inc":false,"votes":1979,"cvotes":"1,979"}],"rd":"55","rd_k":"55","pd_k":"5"}},{"co_id":21011,"name":"Bath","countycode":21011,"race":{"ts":1463595277000,"pctsrep":100,"sw":true,"candidates":[{"id":1445,"fname":"Bernie","mname":"","lname":"Sanders","suffix":"","usesuffix":false,"party":"D","inrace":true,"nominee":false,"winner":false,"vpct":46,"pctDecimal":"46.6","inc":false,"votes":641,"cvotes":"641"},{"id":1746,"fname":"Hillary","mname":"","lname":"Clinton","suffix":"","usesuffix":false,"party":"D","inrace":true,"nominee":true,"winner":true,"vpct":46,"pctDecimal":"45.6","inc":false,"votes":628,"cvotes":"628"}],"rd":"55","rd_k":"55","pd_k":"5"}},{"co_id":21013,"name":"Bell","countycode":21013,"race":{"ts":1463595277000,"pctsrep":100,"sw":true,"candidates":[{"id":1445,"fname":"Bernie","mname":"","lname":"Sanders","suffix":"","usesuffix":false,"party":"D","inrace":true,"nominee":false,"winner":false,"vpct":46,"pctDecimal":"45.6","inc":false,"votes":578,"cvotes":"578"},{"id":1746,"fname":"Hillary","mname":"","lname":"Clinton","suffix":"","usesuffix":false,"party":"D","inrace":true,"nominee":true,"winner":true,"vpct":45,"pctDecimal":"44.7","inc":false,"votes":567,"cvotes":"567"}],"rd":"55","rd_k":"55","pd_k":"5"}},{"co_id":21015,"name":"Boone","countycode":21015,"race":{"ts":1463595277000,"pctsrep":100,"sw":true,"candidates":[{"id":1746,"fname":"Hillary","mname":"","lname":"Clinton","suffix":"","usesuffix":false,"party":"D","inrace":true,"nominee":true,"winner":true,"vpct":52,"pctDecimal":"51.8","inc":false,"votes":2932,"cvotes":"2,932"},{"id":1445,"fname":"Bernie","mname":"","lname":"Sanders","suffix":"","usesuffix":false,"party":"D","inrace":true,"nominee":false,"winner":false,"vpct":44,"pctDecimal":"44.1","inc":false,"votes":2496,"cvotes":"2,496"}],"rd":"55","rd_k":"55","pd_k":"5"}},{"co_id":21017,"name":"Bourbon","countycode":21017,"race":{"ts":1463595277000,"pctsrep":100,"sw":true,"candidates":[{"id":1746,"fname":"Hillary","mname":"","lname":"Clinton","suffix":"","usesuffix":false,"party":"D","inrace":true,"nominee":true,"winner":true,"vpct":46,"pctDecimal":"46.5","inc":false,"votes":1109,"cvotes":"1,109"},{"id":1445,"fname":"Bernie","mname":"","lname":"Sanders","suffix":"","usesuffix":false,"party":"D","inrace":true,"nominee":false,"winner":false,"vpct":46,"pctDecimal":"45.6","inc":false,"votes":1087,"cvotes":"1,087"}],"rd":"55","rd_k":"55","pd_k":"5"}},{"co_id":21019,"name":"Boyd","countycode":21019,"race":{"ts":1463597228000,"pctsrep":100,"sw":true,"candidates":[{"id":1445,"fname":"Bernie","mname":"","lname":"Sanders","suffix":"","usesuffix":false,"party":"D","inrace":true,"nominee":false,"winner":false,"vpct":46,"pctDecimal":"46.1","inc":false,"votes":2262,"cvotes":"2,262"},{"id":1746,"fname":"Hillary","mname":"","lname":"Clinton","suffix":"","usesuffix":false,"party":"D","inrace":true,"nominee":true,"winner":true,"vpct":45,"pctDecimal":"44.7","inc":false,"votes":2193,"cvotes":"2,193"}],"rd":"55","rd_k":"55","pd_k":"5"}},{"co_id":21021,"name":"Boyle","countycode":21021,"race":{"ts":1463595277000,"pctsrep":100,"sw":true,"candidates":[{"id":1746,"fname":"Hillary","mname":"","lname":"Clinton","suffix":"","usesuffix":false,"party":"D","inrace":true,"nominee":true,"winner":true,"vpct":50,"pctDecimal":"49.9","inc":false,"votes":1648,"cvotes":"1,648"},{"id":1445,"fname":"Bernie","mname":"","lname":"Sanders","suffix":"","usesuffix":false,"party":"D","inrace":true,"nominee":false,"winner":false,"vpct":44,"pctDecimal":"43.9","inc":false,"votes":1451,"cvotes":"1,451"}],"rd":"55","rd_k":"55","pd_k":"5"}},{"co_id":21023,"name":"Bracken","countycode":21023,"race":{"ts":1463595277000,"pctsrep":100,"sw":true,"candidates":[{"id":1445,"fname":"Bernie","mname":"","lname":"Sanders","suffix":"","usesuffix":false,"party":"D","inrace":true,"nominee":false,"winner":false,"vpct":55,"pctDecimal":"54.9","inc":false,"votes":424,"cvotes":"424"},{"id":1746,"fname":"Hillary","mname":"","lname":"Clinton","suffix":"","usesuffix":false,"party":"D","inrace":true,"nominee":true,"winner":true,"vpct":33,"pctDecimal":"32.5","inc":false,"votes":251,"cvotes":"251"}],"rd":"55","rd_k":"55","pd_k":"5"}},{"co_id":21025,"name":"Breathitt","countycode":21025,"race":{"ts":1463595277000,"pctsrep":100,"sw":true,"candidates":[{"id":1445,"fname":"Bernie","mname":"","lname":"Sanders","suffix":"","usesuffix":false,"party":"D","inrace":true,"nominee":false,"winner":false,"vpct":52,"pctDecimal":"51.8","inc":false,"votes":1716,"cvotes":"1,716"},{"id":1746,"fname":"Hillary","mname":"","lname":"Clinton","suffix":"","usesuffix":false,"party":"D","inrace":true,"nominee":true,"winner":true,"vpct":34,"pctDecimal":"33.9","inc":false,"votes":1123,"cvotes":"1,123"}],"rd":"55","rd_k":"55","pd_k":"5"}},{"co_id":21027,"name":"Breckinridge","countycode":21027,"race":{"ts":1463595277000,"pctsrep":100,"sw":true,"candidates":[{"id":1746,"fname":"Hillary","mname":"","lname":"Clinton","suffix":"","usesuffix":false,"party":"D","inrace":true,"nominee":true,"winner":true,"vpct":46,"pctDecimal":"45.9","inc":false,"votes":877,"cvotes":"877"},{"id":1445,"fname":"Bernie","mname":"","lname":"Sanders","suffix":"","usesuffix":false,"party":"D","inrace":true,"nominee":false,"winner":false,"vpct":46,"pctDecimal":"45.8","inc":false,"votes":875,"cvotes":"875"}],"rd":"55","rd_k":"55","pd_k":"5"}},{"co_id":21029,"name":"Bullitt","countycode":21029,"race":{"ts":1463595277000,"pctsrep":100,"sw":true,"candidates":[{"id":1445,"fname":"Bernie","mname":"","lname":"Sanders","suffix":"","usesuffix":false,"party":"D","inrace":true,"nominee":false,"winner":false,"vpct":49,"pctDecimal":"49.1","inc":false,"votes":3210,"cvotes":"3,210"},{"id":1746,"fname":"Hillary","mname":"","lname":"Clinton","suffix":"","usesuffix":false,"party":"D","inrace":true,"nominee":true,"winner":true,"vpct":44,"pctDecimal":"44.4","inc":false,"votes":2907,"cvotes":"2,907"}],"rd":"55","rd_k":"55","pd_k":"5"}},{"co_id":21031,"name":"Butler","countycode":21031,"race":{"ts":1463595277000,"pctsrep":100,"sw":true,"candidates":[{"id":1746,"fname":"Hillary","mname":"","lname":"Clinton","suffix":"","usesuffix":false,"party":"D","inrace":true,"nominee":true,"winner":true,"vpct":51,"pctDecimal":"51.1","inc":false,"votes":238,"cvotes":"238"},{"id":1445,"fname":"Bernie","mname":"","lname":"Sanders","suffix":"","usesuffix":false,"party":"D","inrace":true,"nominee":false,"winner":false,"vpct":42,"pctDecimal":"42.1","inc":false,"votes":196,"cvotes":"196"}],"rd":"55","rd_k":"55","pd_k":"5"}},{"co_id":21033,"name":"Caldwell","countycode":21033,"race":{"ts":1463595277000,"pctsrep":100,"sw":true,"candidates":[{"id":1445,"fname":"Bernie","mname":"","lname":"Sanders","suffix":"","usesuffix":false,"party":"D","inrace":true,"nominee":false,"winner":false,"vpct":52,"pctDecimal":"52.1","inc":false,"votes":866,"cvotes":"866"},{"id":1746,"fname":"Hillary","mname":"","lname":"Clinton","suffix":"","usesuffix":false,"party":"D","inrace":true,"nominee":true,"winner":true,"vpct":34,"pctDecimal":"34.3","inc":false,"votes":570,"cvotes":"570"}],"rd":"55","rd_k":"55","pd_k":"5"}},{"co_id":21035,"name":"Calloway","countycode":21035,"race":{"ts":1463595277000,"pctsrep":100,"sw":true,"candidates":[{"id":1445,"fname":"Bernie","mname":"","lname":"Sanders","suffix":"","usesuffix":false,"party":"D","inrace":true,"nominee":false,"winner":false,"vpct":55,"pctDecimal":"55.0","inc":false,"votes":2239,"cvotes":"2,239"},{"id":1746,"fname":"Hillary","mname":"","lname":"Clinton","suffix":"","usesuffix":false,"party":"D","inrace":true,"nominee":true,"winner":true,"vpct":36,"pctDecimal":"35.8","inc":false,"votes":1460,"cvotes":"1,460"}],"rd":"55","rd_k":"55","pd_k":"5"}},{"co_id":21037,"name":"Campbell","countycode":21037,"race":{"ts":1463595277000,"pctsrep":100,"sw":true,"candidates":[{"id":1746,"fname":"Hillary","mname":"","lname":"Clinton","suffix":"","usesuffix":false,"party":"D","inrace":true,"nominee":true,"winner":true,"vpct":48,"pctDecimal":"48.1","inc":false,"votes":3169,"cvotes":"3,169"},{"id":1445,"fname":"Bernie","mname":"","lname":"Sanders","suffix":"","usesuffix":false,"party":"D","inrace":true,"nominee":false,"winner":false,"vpct":48,"pctDecimal":"47.5","inc":false,"votes":3133,"cvotes":"3,133"}],"rd":"55","rd_k":"55","pd_k":"5"}},{"co_id":21039,"name":"Carlisle","countycode":21039,"race":{"ts":1463595277000,"pctsrep":100,"sw":true,"candidates":[{"id":1445,"fname":"Bernie","mname":"","lname":"Sanders","suffix":"","usesuffix":false,"party":"D","inrace":true,"nominee":false,"winner":false,"vpct":57,"pctDecimal":"57.5","inc":false,"votes":462,"cvotes":"462"},{"id":1746,"fname":"Hillary","mname":"","lname":"Clinton","suffix":"","usesuffix":false,"party":"D","inrace":true,"nominee":true,"winner":true,"vpct":26,"pctDecimal":"25.6","inc":false,"votes":206,"cvotes":"206"}],"rd":"55","rd_k":"55","pd_k":"5"}},{"co_id":21041,"name":"Carroll","countycode":21041,"race":{"ts":1463595277000,"pctsrep":100,"sw":true,"candidates":[{"id":1445,"fname":"Bernie","mname":"","lname":"Sanders","suffix":"","usesuffix":false,"party":"D","inrace":true,"nominee":false,"winner":false,"vpct":49,"pctDecimal":"49.4","inc":false,"votes":573,"cvotes":"573"},{"id":1746,"fname":"Hillary","mname":"","lname":"Clinton","suffix":"","usesuffix":false,"party":"D","inrace":true,"nominee":true,"winner":true,"vpct":41,"pctDecimal":"41.5","inc":false,"votes":481,"cvotes":"481"}],"rd":"55","rd_k":"55","pd_k":"5"}},{"co_id":21043,"name":"Carter","countycode":21043,"race":{"ts":1463595277000,"pctsrep":100,"sw":true,"candidates":[{"id":1445,"fname":"Bernie","mname":"","lname":"Sanders","suffix":"","usesuffix":false,"party":"D","inrace":true,"nominee":false,"winner":false,"vpct":51,"pctDecimal":"51.4","inc":false,"votes":1051,"cvotes":"1,051"},{"id":1746,"fname":"Hillary","mname":"","lname":"Clinton","suffix":"","usesuffix":false,"party":"D","inrace":true,"nominee":true,"winner":true,"vpct":39,"pctDecimal":"39.1","inc":false,"votes":800,"cvotes":"800"}],"rd":"55","rd_k":"55","pd_k":"5"}},{"co_id":21045,"name":"Casey","countycode":21045,"race":{"ts":1463595277000,"pctsrep":100,"sw":true,"candidates":[{"id":1746,"fname":"Hillary","mname":"","lname":"Clinton","suffix":"","usesuffix":false,"party":"D","inrace":true,"nominee":true,"winner":true,"vpct":51,"pctDecimal":"50.7","inc":false,"votes":210,"cvotes":"210"},{"id":1445,"fname":"Bernie","mname":"","lname":"Sanders","suffix":"","usesuffix":false,"party":"D","inrace":true,"nominee":false,"winner":false,"vpct":44,"pctDecimal":"44.0","inc":false,"votes":182,"cvotes":"182"}],"rd":"55","rd_k":"55","pd_k":"5"}},{"co_id":21047,"name":"Christian","countycode":21047,"race":{"ts":1463595277000,"pctsrep":100,"sw":true,"candidates":[{"id":1746,"fname":"Hillary","mname":"","lname":"Clinton","suffix":"","usesuffix":false,"party":"D","inrace":true,"nominee":true,"winner":true,"vpct":50,"pctDecimal":"50.2","inc":false,"votes":2437,"cvotes":"2,437"},{"id":1445,"fname":"Bernie","mname":"","lname":"Sanders","suffix":"","usesuffix":false,"party":"D","inrace":true,"nominee":false,"winner":false,"vpct":40,"pctDecimal":"39.9","inc":false,"votes":1936,"cvotes":"1,936"}],"rd":"55","rd_k":"55","pd_k":"5"}},{"co_id":21049,"name":"Clark","countycode":21049,"race":{"ts":1463595277000,"pctsrep":100,"sw":true,"candidates":[{"id":1445,"fname":"Bernie","mname":"","lname":"Sanders","suffix":"","usesuffix":false,"party":"D","inrace":true,"nominee":false,"winner":false,"vpct":47,"pctDecimal":"47.5","inc":false,"votes":1888,"cvotes":"1,888"},{"id":1746,"fname":"Hillary","mname":"","lname":"Clinton","suffix":"","usesuffix":false,"party":"D","inrace":true,"nominee":true,"winner":true,"vpct":46,"pctDecimal":"45.5","inc":false,"votes":1810,"cvotes":"1,810"}],"rd":"55","rd_k":"55","pd_k":"5"}},{"co_id":21051,"name":"Clay","countycode":21051,"race":{"ts":1463595277000,"pctsrep":100,"sw":true,"candidates":[{"id":1746,"fname":"Hillary","mname":"","lname":"Clinton","suffix":"","usesuffix":false,"party":"D","inrace":true,"nominee":true,"winner":true,"vpct":48,"pctDecimal":"48.4","inc":false,"votes":184,"cvotes":"184"},{"id":1445,"fname":"Bernie","mname":"","lname":"Sanders","suffix":"","usesuffix":false,"party":"D","inrace":true,"nominee":false,"winner":false,"vpct":42,"pctDecimal":"41.6","inc":false,"votes":158,"cvotes":"158"}],"rd":"55","rd_k":"55","pd_k":"5"}},{"co_id":21053,"name":"Clinton","countycode":21053,"race":{"ts":1463595277000,"pctsrep":100,"sw":true,"candidates":[{"id":1746,"fname":"Hillary","mname":"","lname":"Clinton","suffix":"","usesuffix":false,"party":"D","inrace":true,"nominee":true,"winner":true,"vpct":58,"pctDecimal":"57.9","inc":false,"votes":151,"cvotes":"151"},{"id":1445,"fname":"Bernie","mname":"","lname":"Sanders","suffix":"","usesuffix":false,"party":"D","inrace":true,"nominee":false,"winner":false,"vpct":36,"pctDecimal":"35.6","inc":false,"votes":93,"cvotes":"93"}],"rd":"55","rd_k":"55","pd_k":"5"}},{"co_id":21055,"name":"Crittenden","countycode":21055,"race":{"ts":1463595277000,"pctsrep":100,"sw":true,"candidates":[{"id":1445,"fname":"Bernie","mname":"","lname":"Sanders","suffix":"","usesuffix":false,"party":"D","inrace":true,"nominee":false,"winner":false,"vpct":51,"pctDecimal":"51.0","inc":false,"votes":344,"cvotes":"344"},{"id":1746,"fname":"Hillary","mname":"","lname":"Clinton","suffix":"","usesuffix":false,"party":"D","inrace":true,"nominee":true,"winner":true,"vpct":36,"pctDecimal":"35.6","inc":false,"votes":240,"cvotes":"240"}],"rd":"55","rd_k":"55","pd_k":"5"}},{"co_id":21057,"name":"Cumberland","countycode":21057,"race":{"ts":1463595277000,"pctsrep":100,"sw":true,"candidates":[{"id":1445,"fname":"Bernie","mname":"","lname":"Sanders","suffix":"","usesuffix":false,"party":"D","inrace":true,"nominee":false,"winner":false,"vpct":50,"pctDecimal":"50.0","inc":false,"votes":87,"cvotes":"87"},{"id":1746,"fname":"Hillary","mname":"","lname":"Clinton","suffix":"","usesuffix":false,"party":"D","inrace":true,"nominee":true,"winner":true,"vpct":45,"pctDecimal":"44.8","inc":false,"votes":78,"cvotes":"78"}],"rd":"55","rd_k":"55","pd_k":"5"}},{"co_id":21059,"name":"Daviess","countycode":21059,"race":{"ts":1463595277000,"pctsrep":100,"sw":true,"candidates":[{"id":1445,"fname":"Bernie","mname":"","lname":"Sanders","suffix":"","usesuffix":false,"party":"D","inrace":true,"nominee":false,"winner":false,"vpct":47,"pctDecimal":"46.6","inc":false,"votes":5188,"cvotes":"5,188"},{"id":1746,"fname":"Hillary","mname":"","lname":"Clinton","suffix":"","usesuffix":false,"party":"D","inrace":true,"nominee":true,"winner":true,"vpct":45,"pctDecimal":"45.5","inc":false,"votes":5066,"cvotes":"5,066"}],"rd":"55","rd_k":"55","pd_k":"5"}},{"co_id":21061,"name":"Edmonson","countycode":21061,"race":{"ts":1463595277000,"pctsrep":100,"sw":true,"candidates":[{"id":1746,"fname":"Hillary","mname":"","lname":"Clinton","suffix":"","usesuffix":false,"party":"D","inrace":true,"nominee":true,"winner":true,"vpct":49,"pctDecimal":"49.5","inc":false,"votes":275,"cvotes":"275"},{"id":1445,"fname":"Bernie","mname":"","lname":"Sanders","suffix":"","usesuffix":false,"party":"D","inrace":true,"nominee":false,"winner":false,"vpct":47,"pctDecimal":"47.1","inc":false,"votes":262,"cvotes":"262"}],"rd":"55","rd_k":"55","pd_k":"5"}},{"co_id":21063,"name":"Elliott","countycode":21063,"race":{"ts":1463595277000,"pctsrep":100,"sw":true,"candidates":[{"id":1445,"fname":"Bernie","mname":"","lname":"Sanders","suffix":"","usesuffix":false,"party":"D","inrace":true,"nominee":false,"winner":false,"vpct":52,"pctDecimal":"52.6","inc":false,"votes":443,"cvotes":"443"},{"id":1746,"fname":"Hillary","mname":"","lname":"Clinton","suffix":"","usesuffix":false,"party":"D","inrace":true,"nominee":true,"winner":true,"vpct":36,"pctDecimal":"35.7","inc":false,"votes":301,"cvotes":"301"}],"rd":"55","rd_k":"55","pd_k":"5"}},{"co_id":21065,"name":"Estill","countycode":21065,"race":{"ts":1463595277000,"pctsrep":100,"sw":true,"candidates":[{"id":1746,"fname":"Hillary","mname":"","lname":"Clinton","suffix":"","usesuffix":false,"party":"D","inrace":true,"nominee":true,"winner":true,"vpct":48,"pctDecimal":"47.6","inc":false,"votes":446,"cvotes":"446"},{"id":1445,"fname":"Bernie","mname":"","lname":"Sanders","suffix":"","usesuffix":false,"party":"D","inrace":true,"nominee":false,"winner":false,"vpct":47,"pctDecimal":"47.0","inc":false,"votes":440,"cvotes":"440"}],"rd":"55","rd_k":"55","pd_k":"5"}},{"co_id":21067,"name":"Fayette","countycode":21067,"race":{"ts":1463595277000,"pctsrep":100,"sw":true,"candidates":[{"id":1746,"fname":"Hillary","mname":"","lname":"Clinton","suffix":"","usesuffix":false,"party":"D","inrace":true,"nominee":true,"winner":true,"vpct":53,"pctDecimal":"52.8","inc":false,"votes":20014,"cvotes":"20,014"},{"id":1445,"fname":"Bernie","mname":"","lname":"Sanders","suffix":"","usesuffix":false,"party":"D","inrace":true,"nominee":false,"winner":false,"vpct":45,"pctDecimal":"45.0","inc":false,"votes":17048,"cvotes":"17,048"}],"rd":"55","rd_k":"55","pd_k":"5"}},{"co_id":21069,"name":"Fleming","countycode":21069,"race":{"ts":1463595277000,"pctsrep":100,"sw":true,"candidates":[{"id":1445,"fname":"Bernie","mname":"","lname":"Sanders","suffix":"","usesuffix":false,"party":"D","inrace":true,"nominee":false,"winner":false,"vpct":52,"pctDecimal":"52.3","inc":false,"votes":806,"cvotes":"806"},{"id":1746,"fname":"Hillary","mname":"","lname":"Clinton","suffix":"","usesuffix":false,"party":"D","inrace":true,"nominee":true,"winner":true,"vpct":41,"pctDecimal":"40.7","inc":false,"votes":627,"cvotes":"627"}],"rd":"55","rd_k":"55","pd_k":"5"}},{"co_id":21071,"name":"Floyd","countycode":21071,"race":{"ts":1463595277000,"pctsrep":100,"sw":true,"candidates":[{"id":1445,"fname":"Bernie","mname":"","lname":"Sanders","suffix":"","usesuffix":false,"party":"D","inrace":true,"nominee":false,"winner":false,"vpct":54,"pctDecimal":"54.1","inc":false,"votes":4010,"cvotes":"4,010"},{"id":1746,"fname":"Hillary","mname":"","lname":"Clinton","suffix":"","usesuffix":false,"party":"D","inrace":true,"nominee":true,"winner":true,"vpct":31,"pctDecimal":"31.4","inc":false,"votes":2327,"cvotes":"2,327"}],"rd":"55","rd_k":"55","pd_k":"5"}},{"co_id":21073,"name":"Franklin","countycode":21073,"race":{"ts":1463600499000,"pctsrep":100,"sw":true,"candidates":[{"id":1445,"fname":"Bernie","mname":"","lname":"Sanders","suffix":"","usesuffix":false,"party":"D","inrace":true,"nominee":false,"winner":false,"vpct":47,"pctDecimal":"46.6","inc":false,"votes":5398,"cvotes":"5,398"},{"id":1746,"fname":"Hillary","mname":"","lname":"Clinton","suffix":"","usesuffix":false,"party":"D","inrace":true,"nominee":true,"winner":true,"vpct":45,"pctDecimal":"45.1","inc":false,"votes":5218,"cvotes":"5,218"}],"rd":"55","rd_k":"55","pd_k":"5"}},{"co_id":21075,"name":"Fulton","countycode":21075,"race":{"ts":1463595277000,"pctsrep":100,"sw":true,"candidates":[{"id":1746,"fname":"Hillary","mname":"","lname":"Clinton","suffix":"","usesuffix":false,"party":"D","inrace":true,"nominee":true,"winner":true,"vpct":47,"pctDecimal":"46.6","inc":false,"votes":315,"cvotes":"315"},{"id":1445,"fname":"Bernie","mname":"","lname":"Sanders","suffix":"","usesuffix":false,"party":"D","inrace":true,"nominee":false,"winner":false,"vpct":36,"pctDecimal":"36.2","inc":false,"votes":245,"cvotes":"245"}],"rd":"55","rd_k":"55","pd_k":"5"}},{"co_id":21077,"name":"Gallatin","countycode":21077,"race":{"ts":1463595277000,"pctsrep":100,"sw":true,"candidates":[{"id":1445,"fname":"Bernie","mname":"","lname":"Sanders","suffix":"","usesuffix":false,"party":"D","inrace":true,"nominee":false,"winner":false,"vpct":52,"pctDecimal":"51.6","inc":false,"votes":340,"cvotes":"340"},{"id":1746,"fname":"Hillary","mname":"","lname":"Clinton","suffix":"","usesuffix":false,"party":"D","inrace":true,"nominee":true,"winner":true,"vpct":39,"pctDecimal":"39.5","inc":false,"votes":260,"cvotes":"260"}],"rd":"55","rd_k":"55","pd_k":"5"}},{"co_id":21079,"name":"Garrard","countycode":21079,"race":{"ts":1463595277000,"pctsrep":100,"sw":true,"candidates":[{"id":1746,"fname":"Hillary","mname":"","lname":"Clinton","suffix":"","usesuffix":false,"party":"D","inrace":true,"nominee":true,"winner":true,"vpct":50,"pctDecimal":"50.5","inc":false,"votes":434,"cvotes":"434"},{"id":1445,"fname":"Bernie","mname":"","lname":"Sanders","suffix":"","usesuffix":false,"party":"D","inrace":true,"nominee":false,"winner":false,"vpct":45,"pctDecimal":"45.0","inc":false,"votes":387,"cvotes":"387"}],"rd":"55","rd_k":"55","pd_k":"5"}},{"co_id":21081,"name":"Grant","countycode":21081,"race":{"ts":1463595277000,"pctsrep":100,"sw":true,"candidates":[{"id":1445,"fname":"Bernie","mname":"","lname":"Sanders","suffix":"","usesuffix":false,"party":"D","inrace":true,"nominee":false,"winner":false,"vpct":49,"pctDecimal":"49.2","inc":false,"votes":715,"cvotes":"715"},{"id":1746,"fname":"Hillary","mname":"","lname":"Clinton","suffix":"","usesuffix":false,"party":"D","inrace":true,"nominee":true,"winner":true,"vpct":41,"pctDecimal":"40.9","inc":false,"votes":594,"cvotes":"594"}],"rd":"55","rd_k":"55","pd_k":"5"}},{"co_id":21083,"name":"Graves","countycode":21083,"race":{"ts":1463595277000,"pctsrep":100,"sw":true,"candidates":[{"id":1445,"fname":"Bernie","mname":"","lname":"Sanders","suffix":"","usesuffix":false,"party":"D","inrace":true,"nominee":false,"winner":false,"vpct":51,"pctDecimal":"51.3","inc":false,"votes":2631,"cvotes":"2,631"},{"id":1746,"fname":"Hillary","mname":"","lname":"Clinton","suffix":"","usesuffix":false,"party":"D","inrace":true,"nominee":true,"winner":true,"vpct":32,"pctDecimal":"31.8","inc":false,"votes":1631,"cvotes":"1,631"}],"rd":"55","rd_k":"55","pd_k":"5"}},{"co_id":21085,"name":"Grayson","countycode":21085,"race":{"ts":1463595277000,"pctsrep":100,"sw":true,"candidates":[{"id":1746,"fname":"Hillary","mname":"","lname":"Clinton","suffix":"","usesuffix":false,"party":"D","inrace":true,"nominee":true,"winner":true,"vpct":50,"pctDecimal":"49.9","inc":false,"votes":705,"cvotes":"705"},{"id":1445,"fname":"Bernie","mname":"","lname":"Sanders","suffix":"","usesuffix":false,"party":"D","inrace":true,"nominee":false,"winner":false,"vpct":45,"pctDecimal":"44.6","inc":false,"votes":630,"cvotes":"630"}],"rd":"55","rd_k":"55","pd_k":"5"}},{"co_id":21087,"name":"Green","countycode":21087,"race":{"ts":1463595277000,"pctsrep":100,"sw":true,"candidates":[{"id":1445,"fname":"Bernie","mname":"","lname":"Sanders","suffix":"","usesuffix":false,"party":"D","inrace":true,"nominee":false,"winner":false,"vpct":51,"pctDecimal":"51.2","inc":false,"votes":360,"cvotes":"360"},{"id":1746,"fname":"Hillary","mname":"","lname":"Clinton","suffix":"","usesuffix":false,"party":"D","inrace":true,"nominee":true,"winner":true,"vpct":40,"pctDecimal":"40.4","inc":false,"votes":284,"cvotes":"284"}],"rd":"55","rd_k":"55","pd_k":"5"}},{"co_id":21089,"name":"Greenup","countycode":21089,"race":{"ts":1463595277000,"pctsrep":100,"sw":true,"candidates":[{"id":1445,"fname":"Bernie","mname":"","lname":"Sanders","suffix":"","usesuffix":false,"party":"D","inrace":true,"nominee":false,"winner":false,"vpct":48,"pctDecimal":"47.7","inc":false,"votes":1655,"cvotes":"1,655"},{"id":1746,"fname":"Hillary","mname":"","lname":"Clinton","suffix":"","usesuffix":false,"party":"D","inrace":true,"nominee":true,"winner":true,"vpct":44,"pctDecimal":"43.8","inc":false,"votes":1517,"cvotes":"1,517"}],"rd":"55","rd_k":"55","pd_k":"5"}},{"co_id":21091,"name":"Hancock","countycode":21091,"race":{"ts":1463596208000,"pctsrep":100,"sw":true,"candidates":[{"id":1445,"fname":"Bernie","mname":"","lname":"Sanders","suffix":"","usesuffix":false,"party":"D","inrace":true,"nominee":false,"winner":false,"vpct":50,"pctDecimal":"49.7","inc":false,"votes":573,"cvotes":"573"},{"id":1746,"fname":"Hillary","mname":"","lname":"Clinton","suffix":"","usesuffix":false,"party":"D","inrace":true,"nominee":true,"winner":true,"vpct":43,"pctDecimal":"42.5","inc":false,"votes":491,"cvotes":"491"}],"rd":"55","rd_k":"55","pd_k":"5"}},{"co_id":21093,"name":"Hardin","countycode":21093,"race":{"ts":1463595277000,"pctsrep":100,"sw":true,"candidates":[{"id":1746,"fname":"Hillary","mname":"","lname":"Clinton","suffix":"","usesuffix":false,"party":"D","inrace":true,"nominee":true,"winner":true,"vpct":48,"pctDecimal":"47.8","inc":false,"votes":4359,"cvotes":"4,359"},{"id":1445,"fname":"Bernie","mname":"","lname":"Sanders","suffix":"","usesuffix":false,"party":"D","inrace":true,"nominee":false,"winner":false,"vpct":46,"pctDecimal":"46.2","inc":false,"votes":4208,"cvotes":"4,208"}],"rd":"55","rd_k":"55","pd_k":"5"}},{"co_id":21095,"name":"Harlan","countycode":21095,"race":{"ts":1463595277000,"pctsrep":100,"sw":true,"candidates":[{"id":1445,"fname":"Bernie","mname":"","lname":"Sanders","suffix":"","usesuffix":false,"party":"D","inrace":true,"nominee":false,"winner":false,"vpct":63,"pctDecimal":"62.8","inc":false,"votes":1092,"cvotes":"1,092"},{"id":1746,"fname":"Hillary","mname":"","lname":"Clinton","suffix":"","usesuffix":false,"party":"D","inrace":true,"nominee":true,"winner":true,"vpct":26,"pctDecimal":"25.9","inc":false,"votes":451,"cvotes":"451"}],"rd":"55","rd_k":"55","pd_k":"5"}},{"co_id":21097,"name":"Harrison","countycode":21097,"race":{"ts":1463595277000,"pctsrep":100,"sw":true,"candidates":[{"id":1445,"fname":"Bernie","mname":"","lname":"Sanders","suffix":"","usesuffix":false,"party":"D","inrace":true,"nominee":false,"winner":false,"vpct":49,"pctDecimal":"49.5","inc":false,"votes":1059,"cvotes":"1,059"},{"id":1746,"fname":"Hillary","mname":"","lname":"Clinton","suffix":"","usesuffix":false,"party":"D","inrace":true,"nominee":true,"winner":true,"vpct":41,"pctDecimal":"41.4","inc":false,"votes":886,"cvotes":"886"}],"rd":"55","rd_k":"55","pd_k":"5"}},{"co_id":21099,"name":"Hart","countycode":21099,"race":{"ts":1463595277000,"pctsrep":100,"sw":true,"candidates":[{"id":1445,"fname":"Bernie","mname":"","lname":"Sanders","suffix":"","usesuffix":false,"party":"D","inrace":true,"nominee":false,"winner":false,"vpct":52,"pctDecimal":"51.6","inc":false,"votes":1062,"cvotes":"1,062"},{"id":1746,"fname":"Hillary","mname":"","lname":"Clinton","suffix":"","usesuffix":false,"party":"D","inrace":true,"nominee":true,"winner":true,"vpct":40,"pctDecimal":"39.7","inc":false,"votes":817,"cvotes":"817"}],"rd":"55","rd_k":"55","pd_k":"5"}},{"co_id":21101,"name":"Henderson","countycode":21101,"race":{"ts":1463595277000,"pctsrep":100,"sw":true,"candidates":[{"id":1746,"fname":"Hillary","mname":"","lname":"Clinton","suffix":"","usesuffix":false,"party":"D","inrace":true,"nominee":true,"winner":true,"vpct":43,"pctDecimal":"43.4","inc":false,"votes":2887,"cvotes":"2,887"},{"id":1445,"fname":"Bernie","mname":"","lname":"Sanders","suffix":"","usesuffix":false,"party":"D","inrace":true,"nominee":false,"winner":false,"vpct":43,"pctDecimal":"42.9","inc":false,"votes":2850,"cvotes":"2,850"}],"rd":"55","rd_k":"55","pd_k":"5"}},{"co_id":21103,"name":"Henry","countycode":21103,"race":{"ts":1463595277000,"pctsrep":100,"sw":true,"candidates":[{"id":1445,"fname":"Bernie","mname":"","lname":"Sanders","suffix":"","usesuffix":false,"party":"D","inrace":true,"nominee":false,"winner":false,"vpct":50,"pctDecimal":"49.8","inc":false,"votes":958,"cvotes":"958"},{"id":1746,"fname":"Hillary","mname":"","lname":"Clinton","suffix":"","usesuffix":false,"party":"D","inrace":true,"nominee":true,"winner":true,"vpct":41,"pctDecimal":"40.6","inc":false,"votes":781,"cvotes":"781"}],"rd":"55","rd_k":"55","pd_k":"5"}},{"co_id":21105,"name":"Hickman","countycode":21105,"race":{"ts":1463595277000,"pctsrep":100,"sw":true,"candidates":[{"id":1445,"fname":"Bernie","mname":"","lname":"Sanders","suffix":"","usesuffix":false,"party":"D","inrace":true,"nominee":false,"winner":false,"vpct":46,"pctDecimal":"46.6","inc":false,"votes":300,"cvotes":"300"},{"id":1746,"fname":"Hillary","mname":"","lname":"Clinton","suffix":"","usesuffix":false,"party":"D","inrace":true,"nominee":true,"winner":true,"vpct":32,"pctDecimal":"32.5","inc":false,"votes":209,"cvotes":"209"}],"rd":"55","rd_k":"55","pd_k":"5"}},{"co_id":21107,"name":"Hopkins","countycode":21107,"race":{"ts":1463595277000,"pctsrep":100,"sw":true,"candidates":[{"id":1445,"fname":"Bernie","mname":"","lname":"Sanders","suffix":"","usesuffix":false,"party":"D","inrace":true,"nominee":false,"winner":false,"vpct":52,"pctDecimal":"52.2","inc":false,"votes":2696,"cvotes":"2,696"},{"id":1746,"fname":"Hillary","mname":"","lname":"Clinton","suffix":"","usesuffix":false,"party":"D","inrace":true,"nominee":true,"winner":true,"vpct":33,"pctDecimal":"32.7","inc":false,"votes":1690,"cvotes":"1,690"}],"rd":"55","rd_k":"55","pd_k":"5"}},{"co_id":21109,"name":"Jackson","countycode":21109,"race":{"ts":1463595277000,"pctsrep":100,"sw":true,"candidates":[{"id":1445,"fname":"Bernie","mname":"","lname":"Sanders","suffix":"","usesuffix":false,"party":"D","inrace":true,"nominee":false,"winner":false,"vpct":59,"pctDecimal":"59.0","inc":false,"votes":128,"cvotes":"128"},{"id":1746,"fname":"Hillary","mname":"","lname":"Clinton","suffix":"","usesuffix":false,"party":"D","inrace":true,"nominee":true,"winner":true,"vpct":36,"pctDecimal":"35.9","inc":false,"votes":78,"cvotes":"78"}],"rd":"55","rd_k":"55","pd_k":"5"}},{"co_id":21111,"name":"Jefferson","countycode":21111,"race":{"ts":1463595277000,"pctsrep":100,"sw":true,"candidates":[{"id":1746,"fname":"Hillary","mname":"","lname":"Clinton","suffix":"","usesuffix":false,"party":"D","inrace":true,"nominee":true,"winner":true,"vpct":57,"pctDecimal":"57.3","inc":false,"votes":64090,"cvotes":"64,090"},{"id":1445,"fname":"Bernie","mname":"","lname":"Sanders","suffix":"","usesuffix":false,"party":"D","inrace":true,"nominee":false,"winner":false,"vpct":40,"pctDecimal":"40.3","inc":false,"votes":45048,"cvotes":"45,048"}],"rd":"55","rd_k":"55","pd_k":"5"}},{"co_id":21113,"name":"Jessamine","countycode":21113,"race":{"ts":1463595277000,"pctsrep":100,"sw":true,"candidates":[{"id":1445,"fname":"Bernie","mname":"","lname":"Sanders","suffix":"","usesuffix":false,"party":"D","inrace":true,"nominee":false,"winner":false,"vpct":50,"pctDecimal":"49.8","inc":false,"votes":2113,"cvotes":"2,113"},{"id":1746,"fname":"Hillary","mname":"","lname":"Clinton","suffix":"","usesuffix":false,"party":"D","inrace":true,"nominee":true,"winner":true,"vpct":44,"pctDecimal":"44.2","inc":false,"votes":1875,"cvotes":"1,875"}],"rd":"55","rd_k":"55","pd_k":"5"}},{"co_id":21115,"name":"Johnson","countycode":21115,"race":{"ts":1463595277000,"pctsrep":100,"sw":true,"candidates":[{"id":1445,"fname":"Bernie","mname":"","lname":"Sanders","suffix":"","usesuffix":false,"party":"D","inrace":true,"nominee":false,"winner":false,"vpct":55,"pctDecimal":"55.5","inc":false,"votes":749,"cvotes":"749"},{"id":1746,"fname":"Hillary","mname":"","lname":"Clinton","suffix":"","usesuffix":false,"party":"D","inrace":true,"nominee":true,"winner":true,"vpct":33,"pctDecimal":"32.9","inc":false,"votes":444,"cvotes":"444"}],"rd":"55","rd_k":"55","pd_k":"5"}},{"co_id":21117,"name":"Kenton","countycode":21117,"race":{"ts":1463595277000,"pctsrep":100,"sw":true,"candidates":[{"id":1746,"fname":"Hillary","mname":"","lname":"Clinton","suffix":"","usesuffix":false,"party":"D","inrace":true,"nominee":true,"winner":true,"vpct":49,"pctDecimal":"49.0","inc":false,"votes":5146,"cvotes":"5,146"},{"id":1445,"fname":"Bernie","mname":"","lname":"Sanders","suffix":"","usesuffix":false,"party":"D","inrace":true,"nominee":false,"winner":false,"vpct":46,"pctDecimal":"46.5","inc":false,"votes":4880,"cvotes":"4,880"}],"rd":"55","rd_k":"55","pd_k":"5"}},{"co_id":21119,"name":"Knott","countycode":21119,"race":{"ts":1463595277000,"pctsrep":100,"sw":true,"candidates":[{"id":1445,"fname":"Bernie","mname":"","lname":"Sanders","suffix":"","usesuffix":false,"party":"D","inrace":true,"nominee":false,"winner":false,"vpct":59,"pctDecimal":"58.8","inc":false,"votes":1114,"cvotes":"1,114"},{"id":1746,"fname":"Hillary","mname":"","lname":"Clinton","suffix":"","usesuffix":false,"party":"D","inrace":true,"nominee":true,"winner":true,"vpct":31,"pctDecimal":"30.8","inc":false,"votes":583,"cvotes":"583"}],"rd":"55","rd_k":"55","pd_k":"5"}},{"co_id":21121,"name":"Knox","countycode":21121,"race":{"ts":1463595277000,"pctsrep":100,"sw":true,"candidates":[{"id":1746,"fname":"Hillary","mname":"","lname":"Clinton","suffix":"","usesuffix":false,"party":"D","inrace":true,"nominee":true,"winner":true,"vpct":48,"pctDecimal":"47.9","inc":false,"votes":520,"cvotes":"520"},{"id":1445,"fname":"Bernie","mname":"","lname":"Sanders","suffix":"","usesuffix":false,"party":"D","inrace":true,"nominee":false,"winner":false,"vpct":46,"pctDecimal":"46.4","inc":false,"votes":504,"cvotes":"504"}],"rd":"55","rd_k":"55","pd_k":"5"}},{"co_id":21123,"name":"LaRue","countycode":21123,"race":{"ts":1463595277000,"pctsrep":100,"sw":true,"candidates":[{"id":1445,"fname":"Bernie","mname":"","lname":"Sanders","suffix":"","usesuffix":false,"party":"D","inrace":true,"nominee":false,"winner":false,"vpct":51,"pctDecimal":"51.6","inc":false,"votes":910,"cvotes":"910"},{"id":1746,"fname":"Hillary","mname":"","lname":"Clinton","suffix":"","usesuffix":false,"party":"D","inrace":true,"nominee":true,"winner":true,"vpct":35,"pctDecimal":"34.7","inc":false,"votes":612,"cvotes":"612"}],"rd":"55","rd_k":"55","pd_k":"5"}},{"co_id":21125,"name":"Laurel","countycode":21125,"race":{"ts":1463595277000,"pctsrep":100,"sw":true,"candidates":[{"id":1746,"fname":"Hillary","mname":"","lname":"Clinton","suffix":"","usesuffix":false,"party":"D","inrace":true,"nominee":true,"winner":true,"vpct":49,"pctDecimal":"49.1","inc":false,"votes":845,"cvotes":"845"},{"id":1445,"fname":"Bernie","mname":"","lname":"Sanders","suffix":"","usesuffix":false,"party":"D","inrace":true,"nominee":false,"winner":false,"vpct":46,"pctDecimal":"45.9","inc":false,"votes":791,"cvotes":"791"}],"rd":"55","rd_k":"55","pd_k":"5"}},{"co_id":21127,"name":"Lawrence","countycode":21127,"race":{"ts":1463595277000,"pctsrep":100,"sw":true,"candidates":[{"id":1445,"fname":"Bernie","mname":"","lname":"Sanders","suffix":"","usesuffix":false,"party":"D","inrace":true,"nominee":false,"winner":false,"vpct":52,"pctDecimal":"52.4","inc":false,"votes":659,"cvotes":"659"},{"id":1746,"fname":"Hillary","mname":"","lname":"Clinton","suffix":"","usesuffix":false,"party":"D","inrace":true,"nominee":true,"winner":true,"vpct":35,"pctDecimal":"35.3","inc":false,"votes":444,"cvotes":"444"}],"rd":"55","rd_k":"55","pd_k":"5"}},{"co_id":21129,"name":"Lee","countycode":21129,"race":{"ts":1463595277000,"pctsrep":100,"sw":true,"candidates":[{"id":1445,"fname":"Bernie","mname":"","lname":"Sanders","suffix":"","usesuffix":false,"party":"D","inrace":true,"nominee":false,"winner":false,"vpct":48,"pctDecimal":"48.3","inc":false,"votes":224,"cvotes":"224"},{"id":1746,"fname":"Hillary","mname":"","lname":"Clinton","suffix":"","usesuffix":false,"party":"D","inrace":true,"nominee":true,"winner":true,"vpct":43,"pctDecimal":"42.9","inc":false,"votes":199,"cvotes":"199"}],"rd":"55","rd_k":"55","pd_k":"5"}},{"co_id":21131,"name":"Leslie","countycode":21131,"race":{"ts":1463595277000,"pctsrep":100,"sw":true,"candidates":[{"id":1445,"fname":"Bernie","mname":"","lname":"Sanders","suffix":"","usesuffix":false,"party":"D","inrace":true,"nominee":false,"winner":false,"vpct":53,"pctDecimal":"52.7","inc":false,"votes":77,"cvotes":"77"},{"id":1746,"fname":"Hillary","mname":"","lname":"Clinton","suffix":"","usesuffix":false,"party":"D","inrace":true,"nominee":true,"winner":true,"vpct":44,"pctDecimal":"43.8","inc":false,"votes":64,"cvotes":"64"}],"rd":"55","rd_k":"55","pd_k":"5"}},{"co_id":21133,"name":"Letcher","countycode":21133,"race":{"ts":1463595277000,"pctsrep":100,"sw":true,"candidates":[{"id":1445,"fname":"Bernie","mname":"","lname":"Sanders","suffix":"","usesuffix":false,"party":"D","inrace":true,"nominee":false,"winner":false,"vpct":57,"pctDecimal":"56.9","inc":false,"votes":1788,"cvotes":"1,788"},{"id":1746,"fname":"Hillary","mname":"","lname":"Clinton","suffix":"","usesuffix":false,"party":"D","inrace":true,"nominee":true,"winner":true,"vpct":27,"pctDecimal":"26.7","inc":false,"votes":838,"cvotes":"838"}],"rd":"55","rd_k":"55","pd_k":"5"}},{"co_id":21135,"name":"Lewis","countycode":21135,"race":{"ts":1463595277000,"pctsrep":100,"sw":true,"candidates":[{"id":1746,"fname":"Hillary","mname":"","lname":"Clinton","suffix":"","usesuffix":false,"party":"D","inrace":true,"nominee":true,"winner":true,"vpct":52,"pctDecimal":"51.7","inc":false,"votes":211,"cvotes":"211"},{"id":1445,"fname":"Bernie","mname":"","lname":"Sanders","suffix":"","usesuffix":false,"party":"D","inrace":true,"nominee":false,"winner":false,"vpct":37,"pctDecimal":"37.0","inc":false,"votes":151,"cvotes":"151"}],"rd":"55","rd_k":"55","pd_k":"5"}},{"co_id":21137,"name":"Lincoln","countycode":21137,"race":{"ts":1463595277000,"pctsrep":100,"sw":true,"candidates":[{"id":1746,"fname":"Hillary","mname":"","lname":"Clinton","suffix":"","usesuffix":false,"party":"D","inrace":true,"nominee":true,"winner":true,"vpct":48,"pctDecimal":"47.7","inc":false,"votes":779,"cvotes":"779"},{"id":1445,"fname":"Bernie","mname":"","lname":"Sanders","suffix":"","usesuffix":false,"party":"D","inrace":true,"nominee":false,"winner":false,"vpct":45,"pctDecimal":"45.5","inc":false,"votes":742,"cvotes":"742"}],"rd":"55","rd_k":"55","pd_k":"5"}},{"co_id":21139,"name":"Livingston","countycode":21139,"race":{"ts":1463596118000,"pctsrep":100,"sw":true,"candidates":[{"id":1445,"fname":"Bernie","mname":"","lname":"Sanders","suffix":"","usesuffix":false,"party":"D","inrace":true,"nominee":false,"winner":false,"vpct":52,"pctDecimal":"52.4","inc":false,"votes":610,"cvotes":"610"},{"id":1746,"fname":"Hillary","mname":"","lname":"Clinton","suffix":"","usesuffix":false,"party":"D","inrace":true,"nominee":true,"winner":true,"vpct":34,"pctDecimal":"34.4","inc":false,"votes":400,"cvotes":"400"}],"rd":"55","rd_k":"55","pd_k":"5"}},{"co_id":21141,"name":"Logan","countycode":21141,"race":{"ts":1463595277000,"pctsrep":100,"sw":true,"candidates":[{"id":1445,"fname":"Bernie","mname":"","lname":"Sanders","suffix":"","usesuffix":false,"party":"D","inrace":true,"nominee":false,"winner":false,"vpct":46,"pctDecimal":"46.0","inc":false,"votes":1131,"cvotes":"1,131"},{"id":1746,"fname":"Hillary","mname":"","lname":"Clinton","suffix":"","usesuffix":false,"party":"D","inrace":true,"nominee":true,"winner":true,"vpct":44,"pctDecimal":"43.8","inc":false,"votes":1077,"cvotes":"1,077"}],"rd":"55","rd_k":"55","pd_k":"5"}},{"co_id":21143,"name":"Lyon","countycode":21143,"race":{"ts":1463595277000,"pctsrep":100,"sw":true,"candidates":[{"id":1445,"fname":"Bernie","mname":"","lname":"Sanders","suffix":"","usesuffix":false,"party":"D","inrace":true,"nominee":false,"winner":false,"vpct":46,"pctDecimal":"45.7","inc":false,"votes":561,"cvotes":"561"},{"id":1746,"fname":"Hillary","mname":"","lname":"Clinton","suffix":"","usesuffix":false,"party":"D","inrace":true,"nominee":true,"winner":true,"vpct":40,"pctDecimal":"40.5","inc":false,"votes":497,"cvotes":"497"}],"rd":"55","rd_k":"55","pd_k":"5"}},{"co_id":21151,"name":"Madison","countycode":21151,"race":{"ts":1463595277000,"pctsrep":100,"sw":true,"candidates":[{"id":1445,"fname":"Bernie","mname":"","lname":"Sanders","suffix":"","usesuffix":false,"party":"D","inrace":true,"nominee":false,"winner":false,"vpct":53,"pctDecimal":"53.0","inc":false,"votes":4385,"cvotes":"4,385"},{"id":1746,"fname":"Hillary","mname":"","lname":"Clinton","suffix":"","usesuffix":false,"party":"D","inrace":true,"nominee":true,"winner":true,"vpct":42,"pctDecimal":"41.6","inc":false,"votes":3441,"cvotes":"3,441"}],"rd":"55","rd_k":"55","pd_k":"5"}},{"co_id":21153,"name":"Magoffin","countycode":21153,"race":{"ts":1463595277000,"pctsrep":100,"sw":true,"candidates":[{"id":1445,"fname":"Bernie","mname":"","lname":"Sanders","suffix":"","usesuffix":false,"party":"D","inrace":true,"nominee":false,"winner":false,"vpct":52,"pctDecimal":"52.3","inc":false,"votes":626,"cvotes":"626"},{"id":1746,"fname":"Hillary","mname":"","lname":"Clinton","suffix":"","usesuffix":false,"party":"D","inrace":true,"nominee":true,"winner":true,"vpct":43,"pctDecimal":"42.7","inc":false,"votes":511,"cvotes":"511"}],"rd":"55","rd_k":"55","pd_k":"5"}},{"co_id":21155,"name":"Marion","countycode":21155,"race":{"ts":1463595277000,"pctsrep":100,"sw":true,"candidates":[{"id":1746,"fname":"Hillary","mname":"","lname":"Clinton","suffix":"","usesuffix":false,"party":"D","inrace":true,"nominee":true,"winner":true,"vpct":50,"pctDecimal":"50.3","inc":false,"votes":1162,"cvotes":"1,162"},{"id":1445,"fname":"Bernie","mname":"","lname":"Sanders","suffix":"","usesuffix":false,"party":"D","inrace":true,"nominee":false,"winner":false,"vpct":43,"pctDecimal":"42.6","inc":false,"votes":983,"cvotes":"983"}],"rd":"55","rd_k":"55","pd_k":"5"}},{"co_id":21157,"name":"Marshall","countycode":21157,"race":{"ts":1463595277000,"pctsrep":100,"sw":true,"candidates":[{"id":1445,"fname":"Bernie","mname":"","lname":"Sanders","suffix":"","usesuffix":false,"party":"D","inrace":true,"nominee":false,"winner":false,"vpct":51,"pctDecimal":"50.8","inc":false,"votes":2308,"cvotes":"2,308"},{"id":1746,"fname":"Hillary","mname":"","lname":"Clinton","suffix":"","usesuffix":false,"party":"D","inrace":true,"nominee":true,"winner":true,"vpct":35,"pctDecimal":"34.7","inc":false,"votes":1577,"cvotes":"1,577"}],"rd":"55","rd_k":"55","pd_k":"5"}},{"co_id":21159,"name":"Martin","countycode":21159,"race":{"ts":1463595277000,"pctsrep":100,"sw":true,"candidates":[{"id":1445,"fname":"Bernie","mname":"","lname":"Sanders","suffix":"","usesuffix":false,"party":"D","inrace":true,"nominee":false,"winner":false,"vpct":57,"pctDecimal":"57.4","inc":false,"votes":191,"cvotes":"191"},{"id":1746,"fname":"Hillary","mname":"","lname":"Clinton","suffix":"","usesuffix":false,"party":"D","inrace":true,"nominee":true,"winner":true,"vpct":31,"pctDecimal":"31.2","inc":false,"votes":104,"cvotes":"104"}],"rd":"55","rd_k":"55","pd_k":"5"}},{"co_id":21161,"name":"Mason","countycode":21161,"race":{"ts":1463595277000,"pctsrep":100,"sw":true,"candidates":[{"id":1445,"fname":"Bernie","mname":"","lname":"Sanders","suffix":"","usesuffix":false,"party":"D","inrace":true,"nominee":false,"winner":false,"vpct":47,"pctDecimal":"47.0","inc":false,"votes":775,"cvotes":"775"},{"id":1746,"fname":"Hillary","mname":"","lname":"Clinton","suffix":"","usesuffix":false,"party":"D","inrace":true,"nominee":true,"winner":true,"vpct":44,"pctDecimal":"44.1","inc":false,"votes":727,"cvotes":"727"}],"rd":"55","rd_k":"55","pd_k":"5"}},{"co_id":21145,"name":"McCracken","countycode":21145,"race":{"ts":1463595277000,"pctsrep":100,"sw":true,"candidates":[{"id":1445,"fname":"Bernie","mname":"","lname":"Sanders","suffix":"","usesuffix":false,"party":"D","inrace":true,"nominee":false,"winner":false,"vpct":46,"pctDecimal":"46.5","inc":false,"votes":3541,"cvotes":"3,541"},{"id":1746,"fname":"Hillary","mname":"","lname":"Clinton","suffix":"","usesuffix":false,"party":"D","inrace":true,"nominee":true,"winner":true,"vpct":44,"pctDecimal":"43.8","inc":false,"votes":3334,"cvotes":"3,334"}],"rd":"55","rd_k":"55","pd_k":"5"}},{"co_id":21147,"name":"McCreary","countycode":21147,"race":{"ts":1463595277000,"pctsrep":100,"sw":true,"candidates":[{"id":1445,"fname":"Bernie","mname":"","lname":"Sanders","suffix":"","usesuffix":false,"party":"D","inrace":true,"nominee":false,"winner":false,"vpct":50,"pctDecimal":"50.4","inc":false,"votes":203,"cvotes":"203"},{"id":1746,"fname":"Hillary","mname":"","lname":"Clinton","suffix":"","usesuffix":false,"party":"D","inrace":true,"nominee":true,"winner":true,"vpct":42,"pctDecimal":"41.9","inc":false,"votes":169,"cvotes":"169"}],"rd":"55","rd_k":"55","pd_k":"5"}},{"co_id":21149,"name":"McLean","countycode":21149,"race":{"ts":1463595277000,"pctsrep":100,"sw":true,"candidates":[{"id":1445,"fname":"Bernie","mname":"","lname":"Sanders","suffix":"","usesuffix":false,"party":"D","inrace":true,"nominee":false,"winner":false,"vpct":50,"pctDecimal":"50.1","inc":false,"votes":628,"cvotes":"628"},{"id":1746,"fname":"Hillary","mname":"","lname":"Clinton","suffix":"","usesuffix":false,"party":"D","inrace":true,"nominee":true,"winner":true,"vpct":38,"pctDecimal":"38.1","inc":false,"votes":477,"cvotes":"477"}],"rd":"55","rd_k":"55","pd_k":"5"}},{"co_id":21163,"name":"Meade","countycode":21163,"race":{"ts":1463595277000,"pctsrep":100,"sw":true,"candidates":[{"id":1445,"fname":"Bernie","mname":"","lname":"Sanders","suffix":"","usesuffix":false,"party":"D","inrace":true,"nominee":false,"winner":false,"vpct":49,"pctDecimal":"49.2","inc":false,"votes":1541,"cvotes":"1,541"},{"id":1746,"fname":"Hillary","mname":"","lname":"Clinton","suffix":"","usesuffix":false,"party":"D","inrace":true,"nominee":true,"winner":true,"vpct":42,"pctDecimal":"41.9","inc":false,"votes":1312,"cvotes":"1,312"}],"rd":"55","rd_k":"55","pd_k":"5"}},{"co_id":21165,"name":"Menifee","countycode":21165,"race":{"ts":1463595277000,"pctsrep":100,"sw":true,"candidates":[{"id":1445,"fname":"Bernie","mname":"","lname":"Sanders","suffix":"","usesuffix":false,"party":"D","inrace":true,"nominee":false,"winner":false,"vpct":47,"pctDecimal":"46.5","inc":false,"votes":323,"cvotes":"323"},{"id":1746,"fname":"Hillary","mname":"","lname":"Clinton","suffix":"","usesuffix":false,"party":"D","inrace":true,"nominee":true,"winner":true,"vpct":45,"pctDecimal":"44.8","inc":false,"votes":311,"cvotes":"311"}],"rd":"55","rd_k":"55","pd_k":"5"}},{"co_id":21167,"name":"Mercer","countycode":21167,"race":{"ts":1463595277000,"pctsrep":100,"sw":true,"candidates":[{"id":1445,"fname":"Bernie","mname":"","lname":"Sanders","suffix":"","usesuffix":false,"party":"D","inrace":true,"nominee":false,"winner":false,"vpct":53,"pctDecimal":"52.6","inc":false,"votes":1331,"cvotes":"1,331"},{"id":1746,"fname":"Hillary","mname":"","lname":"Clinton","suffix":"","usesuffix":false,"party":"D","inrace":true,"nominee":true,"winner":true,"vpct":39,"pctDecimal":"39.1","inc":false,"votes":988,"cvotes":"988"}],"rd":"55","rd_k":"55","pd_k":"5"}},{"co_id":21169,"name":"Metcalfe","countycode":21169,"race":{"ts":1463595277000,"pctsrep":100,"sw":true,"candidates":[{"id":1445,"fname":"Bernie","mname":"","lname":"Sanders","suffix":"","usesuffix":false,"party":"D","inrace":true,"nominee":false,"winner":false,"vpct":48,"pctDecimal":"47.9","inc":false,"votes":582,"cvotes":"582"},{"id":1746,"fname":"Hillary","mname":"","lname":"Clinton","suffix":"","usesuffix":false,"party":"D","inrace":true,"nominee":true,"winner":true,"vpct":42,"pctDecimal":"41.7","inc":false,"votes":506,"cvotes":"506"}],"rd":"55","rd_k":"55","pd_k":"5"}},{"co_id":21171,"name":"Monroe","countycode":21171,"race":{"ts":1463595277000,"pctsrep":100,"sw":true,"candidates":[{"id":1746,"fname":"Hillary","mname":"","lname":"Clinton","suffix":"","usesuffix":false,"party":"D","inrace":true,"nominee":true,"winner":true,"vpct":51,"pctDecimal":"50.8","inc":false,"votes":126,"cvotes":"126"},{"id":1445,"fname":"Bernie","mname":"","lname":"Sanders","suffix":"","usesuffix":false,"party":"D","inrace":true,"nominee":false,"winner":false,"vpct":44,"pctDecimal":"44.0","inc":false,"votes":109,"cvotes":"109"}],"rd":"55","rd_k":"55","pd_k":"5"}},{"co_id":21173,"name":"Montgomery","countycode":21173,"race":{"ts":1463595277000,"pctsrep":100,"sw":true,"candidates":[{"id":1445,"fname":"Bernie","mname":"","lname":"Sanders","suffix":"","usesuffix":false,"party":"D","inrace":true,"nominee":false,"winner":false,"vpct":47,"pctDecimal":"47.0","inc":false,"votes":1322,"cvotes":"1,322"},{"id":1746,"fname":"Hillary","mname":"","lname":"Clinton","suffix":"","usesuffix":false,"party":"D","inrace":true,"nominee":true,"winner":true,"vpct":46,"pctDecimal":"45.8","inc":false,"votes":1289,"cvotes":"1,289"}],"rd":"55","rd_k":"55","pd_k":"5"}},{"co_id":21175,"name":"Morgan","countycode":21175,"race":{"ts":1463595277000,"pctsrep":100,"sw":true,"candidates":[{"id":1445,"fname":"Bernie","mname":"","lname":"Sanders","suffix":"","usesuffix":false,"party":"D","inrace":true,"nominee":false,"winner":false,"vpct":57,"pctDecimal":"57.3","inc":false,"votes":988,"cvotes":"988"},{"id":1746,"fname":"Hillary","mname":"","lname":"Clinton","suffix":"","usesuffix":false,"party":"D","inrace":true,"nominee":true,"winner":true,"vpct":32,"pctDecimal":"31.6","inc":false,"votes":544,"cvotes":"544"}],"rd":"55","rd_k":"55","pd_k":"5"}},{"co_id":21177,"name":"Muhlenberg","countycode":21177,"race":{"ts":1463595277000,"pctsrep":100,"sw":true,"candidates":[{"id":1445,"fname":"Bernie","mname":"","lname":"Sanders","suffix":"","usesuffix":false,"party":"D","inrace":true,"nominee":false,"winner":false,"vpct":46,"pctDecimal":"45.7","inc":false,"votes":1632,"cvotes":"1,632"},{"id":1746,"fname":"Hillary","mname":"","lname":"Clinton","suffix":"","usesuffix":false,"party":"D","inrace":true,"nominee":true,"winner":true,"vpct":43,"pctDecimal":"43.3","inc":false,"votes":1544,"cvotes":"1,544"}],"rd":"55","rd_k":"55","pd_k":"5"}},{"co_id":21179,"name":"Nelson","countycode":21179,"race":{"ts":1463595277000,"pctsrep":100,"sw":true,"candidates":[{"id":1746,"fname":"Hillary","mname":"","lname":"Clinton","suffix":"","usesuffix":false,"party":"D","inrace":true,"nominee":true,"winner":true,"vpct":48,"pctDecimal":"47.6","inc":false,"votes":2395,"cvotes":"2,395"},{"id":1445,"fname":"Bernie","mname":"","lname":"Sanders","suffix":"","usesuffix":false,"party":"D","inrace":true,"nominee":false,"winner":false,"vpct":47,"pctDecimal":"46.6","inc":false,"votes":2345,"cvotes":"2,345"}],"rd":"55","rd_k":"55","pd_k":"5"}},{"co_id":21181,"name":"Nicholas","countycode":21181,"race":{"ts":1463595277000,"pctsrep":100,"sw":true,"candidates":[{"id":1445,"fname":"Bernie","mname":"","lname":"Sanders","suffix":"","usesuffix":false,"party":"D","inrace":true,"nominee":false,"winner":false,"vpct":50,"pctDecimal":"50.2","inc":false,"votes":420,"cvotes":"420"},{"id":1746,"fname":"Hillary","mname":"","lname":"Clinton","suffix":"","usesuffix":false,"party":"D","inrace":true,"nominee":true,"winner":true,"vpct":42,"pctDecimal":"42.2","inc":false,"votes":353,"cvotes":"353"}],"rd":"55","rd_k":"55","pd_k":"5"}},{"co_id":21183,"name":"Ohio","countycode":21183,"race":{"ts":1463595277000,"pctsrep":100,"sw":true,"candidates":[{"id":1445,"fname":"Bernie","mname":"","lname":"Sanders","suffix":"","usesuffix":false,"party":"D","inrace":true,"nominee":false,"winner":false,"vpct":50,"pctDecimal":"50.0","inc":false,"votes":943,"cvotes":"943"},{"id":1746,"fname":"Hillary","mname":"","lname":"Clinton","suffix":"","usesuffix":false,"party":"D","inrace":true,"nominee":true,"winner":true,"vpct":41,"pctDecimal":"41.3","inc":false,"votes":778,"cvotes":"778"}],"rd":"55","rd_k":"55","pd_k":"5"}},{"co_id":21185,"name":"Oldham","countycode":21185,"race":{"ts":1463595277000,"pctsrep":100,"sw":true,"candidates":[{"id":1746,"fname":"Hillary","mname":"","lname":"Clinton","suffix":"","usesuffix":false,"party":"D","inrace":true,"nominee":true,"winner":true,"vpct":52,"pctDecimal":"52.4","inc":false,"votes":2730,"cvotes":"2,730"},{"id":1445,"fname":"Bernie","mname":"","lname":"Sanders","suffix":"","usesuffix":false,"party":"D","inrace":true,"nominee":false,"winner":false,"vpct":44,"pctDecimal":"44.4","inc":false,"votes":2315,"cvotes":"2,315"}],"rd":"55","rd_k":"55","pd_k":"5"}},{"co_id":21187,"name":"Owen","countycode":21187,"race":{"ts":1463595277000,"pctsrep":100,"sw":true,"candidates":[{"id":1445,"fname":"Bernie","mname":"","lname":"Sanders","suffix":"","usesuffix":false,"party":"D","inrace":true,"nominee":false,"winner":false,"vpct":55,"pctDecimal":"55.0","inc":false,"votes":720,"cvotes":"720"},{"id":1746,"fname":"Hillary","mname":"","lname":"Clinton","suffix":"","usesuffix":false,"party":"D","inrace":true,"nominee":true,"winner":true,"vpct":35,"pctDecimal":"34.6","inc":false,"votes":453,"cvotes":"453"}],"rd":"55","rd_k":"55","pd_k":"5"}},{"co_id":21189,"name":"Owsley","countycode":21189,"race":{"ts":1463595277000,"pctsrep":100,"sw":true,"candidates":[{"id":1445,"fname":"Bernie","mname":"","lname":"Sanders","suffix":"","usesuffix":false,"party":"D","inrace":true,"nominee":false,"winner":false,"vpct":51,"pctDecimal":"51.1","inc":false,"votes":91,"cvotes":"91"},{"id":1746,"fname":"Hillary","mname":"","lname":"Clinton","suffix":"","usesuffix":false,"party":"D","inrace":true,"nominee":true,"winner":true,"vpct":43,"pctDecimal":"43.3","inc":false,"votes":77,"cvotes":"77"}],"rd":"55","rd_k":"55","pd_k":"5"}},{"co_id":21191,"name":"Pendleton","countycode":21191,"race":{"ts":1463595277000,"pctsrep":100,"sw":true,"candidates":[{"id":1445,"fname":"Bernie","mname":"","lname":"Sanders","suffix":"","usesuffix":false,"party":"D","inrace":true,"nominee":false,"winner":false,"vpct":51,"pctDecimal":"51.5","inc":false,"votes":546,"cvotes":"546"},{"id":1746,"fname":"Hillary","mname":"","lname":"Clinton","suffix":"","usesuffix":false,"party":"D","inrace":true,"nominee":true,"winner":true,"vpct":37,"pctDecimal":"36.6","inc":false,"votes":388,"cvotes":"388"}],"rd":"55","rd_k":"55","pd_k":"5"}},{"co_id":21193,"name":"Perry","countycode":21193,"race":{"ts":1463595277000,"pctsrep":100,"sw":true,"candidates":[{"id":1445,"fname":"Bernie","mname":"","lname":"Sanders","suffix":"","usesuffix":false,"party":"D","inrace":true,"nominee":false,"winner":false,"vpct":60,"pctDecimal":"59.6","inc":false,"votes":1666,"cvotes":"1,666"},{"id":1746,"fname":"Hillary","mname":"","lname":"Clinton","suffix":"","usesuffix":false,"party":"D","inrace":true,"nominee":true,"winner":true,"vpct":30,"pctDecimal":"30.0","inc":false,"votes":839,"cvotes":"839"}],"rd":"55","rd_k":"55","pd_k":"5"}},{"co_id":21195,"name":"Pike","countycode":21195,"race":{"ts":1463595277000,"pctsrep":100,"sw":true,"candidates":[{"id":1445,"fname":"Bernie","mname":"","lname":"Sanders","suffix":"","usesuffix":false,"party":"D","inrace":true,"nominee":false,"winner":false,"vpct":54,"pctDecimal":"54.3","inc":false,"votes":4848,"cvotes":"4,848"},{"id":1746,"fname":"Hillary","mname":"","lname":"Clinton","suffix":"","usesuffix":false,"party":"D","inrace":true,"nominee":true,"winner":true,"vpct":26,"pctDecimal":"26.1","inc":false,"votes":2335,"cvotes":"2,335"}],"rd":"55","rd_k":"55","pd_k":"5"}},{"co_id":21197,"name":"Powell","countycode":21197,"race":{"ts":1463595277000,"pctsrep":100,"sw":true,"candidates":[{"id":1445,"fname":"Bernie","mname":"","lname":"Sanders","suffix":"","usesuffix":false,"party":"D","inrace":true,"nominee":false,"winner":false,"vpct":51,"pctDecimal":"50.7","inc":false,"votes":744,"cvotes":"744"},{"id":1746,"fname":"Hillary","mname":"","lname":"Clinton","suffix":"","usesuffix":false,"party":"D","inrace":true,"nominee":true,"winner":true,"vpct":42,"pctDecimal":"42.4","inc":false,"votes":623,"cvotes":"623"}],"rd":"55","rd_k":"55","pd_k":"5"}},{"co_id":21199,"name":"Pulaski","countycode":21199,"race":{"ts":1463595277000,"pctsrep":100,"sw":true,"candidates":[{"id":1746,"fname":"Hillary","mname":"","lname":"Clinton","suffix":"","usesuffix":false,"party":"D","inrace":true,"nominee":true,"winner":true,"vpct":47,"pctDecimal":"47.4","inc":false,"votes":1169,"cvotes":"1,169"},{"id":1445,"fname":"Bernie","mname":"","lname":"Sanders","suffix":"","usesuffix":false,"party":"D","inrace":true,"nominee":false,"winner":false,"vpct":47,"pctDecimal":"46.6","inc":false,"votes":1148,"cvotes":"1,148"}],"rd":"55","rd_k":"55","pd_k":"5"}},{"co_id":21201,"name":"Robertson","countycode":21201,"race":{"ts":1463595277000,"pctsrep":100,"sw":true,"candidates":[{"id":1445,"fname":"Bernie","mname":"","lname":"Sanders","suffix":"","usesuffix":false,"party":"D","inrace":true,"nominee":false,"winner":false,"vpct":59,"pctDecimal":"59.6","inc":false,"votes":177,"cvotes":"177"},{"id":1746,"fname":"Hillary","mname":"","lname":"Clinton","suffix":"","usesuffix":false,"party":"D","inrace":true,"nominee":true,"winner":true,"vpct":32,"pctDecimal":"32.0","inc":false,"votes":95,"cvotes":"95"}],"rd":"55","rd_k":"55","pd_k":"5"}},{"co_id":21203,"name":"Rockcastle","countycode":21203,"race":{"ts":1463595277000,"pctsrep":100,"sw":true,"candidates":[{"id":1445,"fname":"Bernie","mname":"","lname":"Sanders","suffix":"","usesuffix":false,"party":"D","inrace":true,"nominee":false,"winner":false,"vpct":49,"pctDecimal":"48.8","inc":false,"votes":254,"cvotes":"254"},{"id":1746,"fname":"Hillary","mname":"","lname":"Clinton","suffix":"","usesuffix":false,"party":"D","inrace":true,"nominee":true,"winner":true,"vpct":46,"pctDecimal":"45.7","inc":false,"votes":238,"cvotes":"238"}],"rd":"55","rd_k":"55","pd_k":"5"}},{"co_id":21205,"name":"Rowan","countycode":21205,"race":{"ts":1463595277000,"pctsrep":100,"sw":true,"candidates":[{"id":1445,"fname":"Bernie","mname":"","lname":"Sanders","suffix":"","usesuffix":false,"party":"D","inrace":true,"nominee":false,"winner":false,"vpct":51,"pctDecimal":"51.2","inc":false,"votes":1363,"cvotes":"1,363"},{"id":1746,"fname":"Hillary","mname":"","lname":"Clinton","suffix":"","usesuffix":false,"party":"D","inrace":true,"nominee":true,"winner":true,"vpct":44,"pctDecimal":"44.0","inc":false,"votes":1170,"cvotes":"1,170"}],"rd":"55","rd_k":"55","pd_k":"5"}},{"co_id":21207,"name":"Russell","countycode":21207,"race":{"ts":1463600018000,"pctsrep":100,"sw":true,"candidates":[{"id":1746,"fname":"Hillary","mname":"","lname":"Clinton","suffix":"","usesuffix":false,"party":"D","inrace":true,"nominee":true,"winner":true,"vpct":48,"pctDecimal":"48.2","inc":false,"votes":343,"cvotes":"343"},{"id":1445,"fname":"Bernie","mname":"","lname":"Sanders","suffix":"","usesuffix":false,"party":"D","inrace":true,"nominee":false,"winner":false,"vpct":47,"pctDecimal":"46.7","inc":false,"votes":332,"cvotes":"332"}],"rd":"55","rd_k":"55","pd_k":"5"}},{"co_id":21209,"name":"Scott","countycode":21209,"race":{"ts":1463595277000,"pctsrep":100,"sw":true,"candidates":[{"id":1746,"fname":"Hillary","mname":"","lname":"Clinton","suffix":"","usesuffix":false,"party":"D","inrace":true,"nominee":true,"winner":true,"vpct":49,"pctDecimal":"48.6","inc":false,"votes":2505,"cvotes":"2,505"},{"id":1445,"fname":"Bernie","mname":"","lname":"Sanders","suffix":"","usesuffix":false,"party":"D","inrace":true,"nominee":false,"winner":false,"vpct":46,"pctDecimal":"46.4","inc":false,"votes":2394,"cvotes":"2,394"}],"rd":"55","rd_k":"55","pd_k":"5"}},{"co_id":21211,"name":"Shelby","countycode":21211,"race":{"ts":1463595277000,"pctsrep":100,"sw":true,"candidates":[{"id":1746,"fname":"Hillary","mname":"","lname":"Clinton","suffix":"","usesuffix":false,"party":"D","inrace":true,"nominee":true,"winner":true,"vpct":48,"pctDecimal":"47.8","inc":false,"votes":2195,"cvotes":"2,195"},{"id":1445,"fname":"Bernie","mname":"","lname":"Sanders","suffix":"","usesuffix":false,"party":"D","inrace":true,"nominee":false,"winner":false,"vpct":44,"pctDecimal":"44.5","inc":false,"votes":2044,"cvotes":"2,044"}],"rd":"55","rd_k":"55","pd_k":"5"}},{"co_id":21213,"name":"Simpson","countycode":21213,"race":{"ts":1463595277000,"pctsrep":100,"sw":true,"candidates":[{"id":1746,"fname":"Hillary","mname":"","lname":"Clinton","suffix":"","usesuffix":false,"party":"D","inrace":true,"nominee":true,"winner":true,"vpct":46,"pctDecimal":"45.9","inc":false,"votes":708,"cvotes":"708"},{"id":1445,"fname":"Bernie","mname":"","lname":"Sanders","suffix":"","usesuffix":false,"party":"D","inrace":true,"nominee":false,"winner":false,"vpct":45,"pctDecimal":"45.1","inc":false,"votes":695,"cvotes":"695"}],"rd":"55","rd_k":"55","pd_k":"5"}},{"co_id":21215,"name":"Spencer","countycode":21215,"race":{"ts":1463596328000,"pctsrep":100,"sw":true,"candidates":[{"id":1445,"fname":"Bernie","mname":"","lname":"Sanders","suffix":"","usesuffix":false,"party":"D","inrace":true,"nominee":false,"winner":false,"vpct":51,"pctDecimal":"51.2","inc":false,"votes":806,"cvotes":"806"},{"id":1746,"fname":"Hillary","mname":"","lname":"Clinton","suffix":"","usesuffix":false,"party":"D","inrace":true,"nominee":true,"winner":true,"vpct":43,"pctDecimal":"42.7","inc":false,"votes":673,"cvotes":"673"}],"rd":"55","rd_k":"55","pd_k":"5"}},{"co_id":21217,"name":"Taylor","countycode":21217,"race":{"ts":1463595277000,"pctsrep":100,"sw":true,"candidates":[{"id":1746,"fname":"Hillary","mname":"","lname":"Clinton","suffix":"","usesuffix":false,"party":"D","inrace":true,"nominee":true,"winner":true,"vpct":50,"pctDecimal":"50.3","inc":false,"votes":949,"cvotes":"949"},{"id":1445,"fname":"Bernie","mname":"","lname":"Sanders","suffix":"","usesuffix":false,"party":"D","inrace":true,"nominee":false,"winner":false,"vpct":45,"pctDecimal":"44.8","inc":false,"votes":844,"cvotes":"844"}],"rd":"55","rd_k":"55","pd_k":"5"}},{"co_id":21219,"name":"Todd","countycode":21219,"race":{"ts":1463595277000,"pctsrep":100,"sw":true,"candidates":[{"id":1445,"fname":"Bernie","mname":"","lname":"Sanders","suffix":"","usesuffix":false,"party":"D","inrace":true,"nominee":false,"winner":false,"vpct":53,"pctDecimal":"53.5","inc":false,"votes":507,"cvotes":"507"},{"id":1746,"fname":"Hillary","mname":"","lname":"Clinton","suffix":"","usesuffix":false,"party":"D","inrace":true,"nominee":true,"winner":true,"vpct":35,"pctDecimal":"35.1","inc":false,"votes":333,"cvotes":"333"}],"rd":"55","rd_k":"55","pd_k":"5"}},{"co_id":21221,"name":"Trigg","countycode":21221,"race":{"ts":1463595277000,"pctsrep":100,"sw":true,"candidates":[{"id":1445,"fname":"Bernie","mname":"","lname":"Sanders","suffix":"","usesuffix":false,"party":"D","inrace":true,"nominee":false,"winner":false,"vpct":48,"pctDecimal":"48.3","inc":false,"votes":715,"cvotes":"715"},{"id":1746,"fname":"Hillary","mname":"","lname":"Clinton","suffix":"","usesuffix":false,"party":"D","inrace":true,"nominee":true,"winner":true,"vpct":41,"pctDecimal":"40.8","inc":false,"votes":604,"cvotes":"604"}],"rd":"55","rd_k":"55","pd_k":"5"}},{"co_id":21223,"name":"Trimble","countycode":21223,"race":{"ts":1463595277000,"pctsrep":100,"sw":true,"candidates":[{"id":1445,"fname":"Bernie","mname":"","lname":"Sanders","suffix":"","usesuffix":false,"party":"D","inrace":true,"nominee":false,"winner":false,"vpct":50,"pctDecimal":"50.0","inc":false,"votes":542,"cvotes":"542"},{"id":1746,"fname":"Hillary","mname":"","lname":"Clinton","suffix":"","usesuffix":false,"party":"D","inrace":true,"nominee":true,"winner":true,"vpct":38,"pctDecimal":"38.3","inc":false,"votes":415,"cvotes":"415"}],"rd":"55","rd_k":"55","pd_k":"5"}},{"co_id":21225,"name":"Union","countycode":21225,"race":{"ts":1463595277000,"pctsrep":100,"sw":true,"candidates":[{"id":1445,"fname":"Bernie","mname":"","lname":"Sanders","suffix":"","usesuffix":false,"party":"D","inrace":true,"nominee":false,"winner":false,"vpct":49,"pctDecimal":"49.3","inc":false,"votes":1106,"cvotes":"1,106"},{"id":1746,"fname":"Hillary","mname":"","lname":"Clinton","suffix":"","usesuffix":false,"party":"D","inrace":true,"nominee":true,"winner":true,"vpct":30,"pctDecimal":"29.9","inc":false,"votes":672,"cvotes":"672"}],"rd":"55","rd_k":"55","pd_k":"5"}},{"co_id":21227,"name":"Warren","countycode":21227,"race":{"ts":1463595277000,"pctsrep":100,"sw":true,"candidates":[{"id":1445,"fname":"Bernie","mname":"","lname":"Sanders","suffix":"","usesuffix":false,"party":"D","inrace":true,"nominee":false,"winner":false,"vpct":50,"pctDecimal":"49.9","inc":false,"votes":5365,"cvotes":"5,365"},{"id":1746,"fname":"Hillary","mname":"","lname":"Clinton","suffix":"","usesuffix":false,"party":"D","inrace":true,"nominee":true,"winner":true,"vpct":45,"pctDecimal":"44.9","inc":false,"votes":4829,"cvotes":"4,829"}],"rd":"55","rd_k":"55","pd_k":"5"}},{"co_id":21229,"name":"Washington","countycode":21229,"race":{"ts":1463595277000,"pctsrep":100,"sw":true,"candidates":[{"id":1746,"fname":"Hillary","mname":"","lname":"Clinton","suffix":"","usesuffix":false,"party":"D","inrace":true,"nominee":true,"winner":true,"vpct":47,"pctDecimal":"47.0","inc":false,"votes":601,"cvotes":"601"},{"id":1445,"fname":"Bernie","mname":"","lname":"Sanders","suffix":"","usesuffix":false,"party":"D","inrace":true,"nominee":false,"winner":false,"vpct":45,"pctDecimal":"45.5","inc":false,"votes":582,"cvotes":"582"}],"rd":"55","rd_k":"55","pd_k":"5"}},{"co_id":21231,"name":"Wayne","countycode":21231,"race":{"ts":1463595277000,"pctsrep":100,"sw":true,"candidates":[{"id":1746,"fname":"Hillary","mname":"","lname":"Clinton","suffix":"","usesuffix":false,"party":"D","inrace":true,"nominee":true,"winner":true,"vpct":56,"pctDecimal":"55.6","inc":false,"votes":502,"cvotes":"502"},{"id":1445,"fname":"Bernie","mname":"","lname":"Sanders","suffix":"","usesuffix":false,"party":"D","inrace":true,"nominee":false,"winner":false,"vpct":39,"pctDecimal":"39.4","inc":false,"votes":356,"cvotes":"356"}],"rd":"55","rd_k":"55","pd_k":"5"}},{"co_id":21233,"name":"Webster","countycode":21233,"race":{"ts":1463595277000,"pctsrep":100,"sw":true,"candidates":[{"id":1445,"fname":"Bernie","mname":"","lname":"Sanders","suffix":"","usesuffix":false,"party":"D","inrace":true,"nominee":false,"winner":false,"vpct":48,"pctDecimal":"48.5","inc":false,"votes":1169,"cvotes":"1,169"},{"id":1746,"fname":"Hillary","mname":"","lname":"Clinton","suffix":"","usesuffix":false,"party":"D","inrace":true,"nominee":true,"winner":true,"vpct":29,"pctDecimal":"28.7","inc":false,"votes":693,"cvotes":"693"}],"rd":"55","rd_k":"55","pd_k":"5"}},{"co_id":21235,"name":"Whitley","countycode":21235,"race":{"ts":1463596088000,"pctsrep":100,"sw":true,"candidates":[{"id":1746,"fname":"Hillary","mname":"","lname":"Clinton","suffix":"","usesuffix":false,"party":"D","inrace":true,"nominee":true,"winner":true,"vpct":53,"pctDecimal":"52.5","inc":false,"votes":522,"cvotes":"522"},{"id":1445,"fname":"Bernie","mname":"","lname":"Sanders","suffix":"","usesuffix":false,"party":"D","inrace":true,"nominee":false,"winner":false,"vpct":41,"pctDecimal":"41.1","inc":false,"votes":409,"cvotes":"409"}],"rd":"55","rd_k":"55","pd_k":"5"}},{"co_id":21237,"name":"Wolfe","countycode":21237,"race":{"ts":1463595277000,"pctsrep":100,"sw":true,"candidates":[{"id":1445,"fname":"Bernie","mname":"","lname":"Sanders","suffix":"","usesuffix":false,"party":"D","inrace":true,"nominee":false,"winner":false,"vpct":51,"pctDecimal":"50.7","inc":false,"votes":499,"cvotes":"499"},{"id":1746,"fname":"Hillary","mname":"","lname":"Clinton","suffix":"","usesuffix":false,"party":"D","inrace":true,"nominee":true,"winner":true,"vpct":42,"pctDecimal":"42.1","inc":false,"votes":414,"cvotes":"414"}],"rd":"55","rd_k":"55","pd_k":"5"}},{"co_id":21239,"name":"Woodford","countycode":21239,"race":{"ts":1463596118000,"pctsrep":100,"sw":true,"candidates":[{"id":1445,"fname":"Bernie","mname":"","lname":"Sanders","suffix":"","usesuffix":false,"party":"D","inrace":true,"nominee":false,"winner":false,"vpct":48,"pctDecimal":"47.7","inc":false,"votes":1918,"cvotes":"1,918"},{"id":1746,"fname":"Hillary","mname":"","lname":"Clinton","suffix":"","usesuffix":false,"party":"D","inrace":true,"nominee":true,"winner":true,"vpct":46,"pctDecimal":"46.3","inc":false,"votes":1862,"cvotes":"1,862"}],"rd":"55","rd_k":"55","pd_k":"5"}}],"lts":1463600499000}